pdf2dcm/__init__.py
pdf2dcm/base.py
pdf2dcm/pdf2encaps.py
pdf2dcm/pdf2rgb.py
pdf2dcm/utils/uid.py
pdf2dcm-0.5.2.dist-info/LICENSE
pdf2dcm-0.5.2.dist-info/METADATA
pdf2dcm-0.5.2.dist-info/WHEEL
pdf2dcm-0.5.2.dist-info/RECORD
