Metadata-Version: 2.1
Name: pdf2dcm
Version: 0.5.2
Summary: A PDF to Dicom Converter
Home-page: https://a-parida12.github.io/pdf2dcm/
License: MIT
Keywords: dicom,pdf,pdf2dcm,pdf2dicom,pydicom,pdf2dicomRGB
Author: Abhijeet Parida
Author-email: abhijeet.parida@tum.de
Requires-Python: >=3.8,<4.0
Classifier: License :: OSI Approved :: MIT License
Classifier: Programming Language :: Python :: 3
Classifier: Programming Language :: Python :: 3.8
Classifier: Programming Language :: Python :: 3.9
Classifier: Programming Language :: Python :: 3.10
Classifier: Programming Language :: Python :: 3.11
Classifier: Programming Language :: Python :: 3.12
Classifier: Programming Language :: Python :: 3.13
Requires-Dist: pdf2image (>=1.16.3,<2.0.0)
Requires-Dist: pillow (>=9.5,<11.0)
Requires-Dist: pydicom (>=2.3.0,<3.0.0)
Project-URL: Repository, https://github.com/a-parida12/pdf2dcm
